superdelegate/__init__.py
superdelegate/__version__.py
superdelegate/tests.py
superdelegate-0.0.2.dist-info/LICENSE
superdelegate-0.0.2.dist-info/METADATA
superdelegate-0.0.2.dist-info/WHEEL
superdelegate-0.0.2.dist-info/top_level.txt
superdelegate-0.0.2.dist-info/RECORD
