Metadata-Version: 2.1
Name: superdelegate
Version: 0.0.2
Summary: Delegate methods and properties to child objects in a terse, explicit style
Home-page: https://github.com/bgschiller/superdelegate
Author: Brian Schiller
Author-email: bgschiller@gmail.com
License: MIT
Platform: UNKNOWN
Classifier: License :: OSI Approved :: MIT License
Classifier: Programming Language :: Python
Classifier: Programming Language :: Python :: 3
Classifier: Programming Language :: Python :: 3.6
Classifier: Programming Language :: Python :: Implementation :: CPython
Classifier: Programming Language :: Python :: Implementation :: PyPy
Requires-Python: >=3.2.6
